web2img_deltabot/__init__.py
web2img_deltabot/__main__.py
web2img_deltabot/_version.py
web2img_deltabot/hooks.py
web2img_deltabot/utils.py
web2img_deltabot-1.1.0.dist-info/LICENSE
web2img_deltabot-1.1.0.dist-info/METADATA
web2img_deltabot-1.1.0.dist-info/WHEEL
web2img_deltabot-1.1.0.dist-info/entry_points.txt
web2img_deltabot-1.1.0.dist-info/top_level.txt
web2img_deltabot-1.1.0.dist-info/RECORD
